<?xml version="1.0" encoding="UTF-8"?>
<sv:node sv:name="createSupplier" xmlns:sv="http://www.jcp.org/jcr/sv/1.0" xmlns:xsi="http://www.w3.org/2001/XMLSchema-instance">
  <sv:property sv:name="jcr:primaryType" sv:type="Name">
    <sv:value>mgnl:contentNode</sv:value>
  </sv:property>
  <sv:property sv:name="jcr:mixinTypes" sv:type="Name" sv:multiple="true">
    <sv:value>mix:lockable</sv:value>
  </sv:property>
  <sv:property sv:name="jcr:uuid" sv:type="String">
    <sv:value>b0ddee59-3709-49d2-994c-7fbf06994f42</sv:value>
  </sv:property>
  <sv:property sv:name="jcr:createdBy" sv:type="String">
    <sv:value>admin</sv:value>
  </sv:property>
  <sv:property sv:name="mgnl:created" sv:type="Date">
    <sv:value>2012-05-27T21:13:38.604+02:00</sv:value>
  </sv:property>
  <sv:property sv:name="mgnl:lastModified" sv:type="Date">
    <sv:value>2013-10-20T09:01:08.850+02:00</sv:value>
  </sv:property>
  <sv:property sv:name="mgnl:lastModifiedBy" sv:type="String">
    <sv:value>superuser</sv:value>
  </sv:property>
  <sv:node sv:name="actions">
    <sv:property sv:name="jcr:primaryType" sv:type="Name">
      <sv:value>mgnl:contentNode</sv:value>
    </sv:property>
    <sv:property sv:name="jcr:uuid" sv:type="String">
      <sv:value>6b6eb1b9-44db-4c6f-afcc-32b4e1ee9b35</sv:value>
    </sv:property>
    <sv:property sv:name="jcr:createdBy" sv:type="String">
      <sv:value>admin</sv:value>
    </sv:property>
    <sv:property sv:name="mgnl:lastModified" sv:type="Date">
      <sv:value>2013-10-20T09:01:08.844+02:00</sv:value>
    </sv:property>
    <sv:property sv:name="mgnl:lastModifiedBy" sv:type="String">
      <sv:value>superuser</sv:value>
    </sv:property>
    <sv:node sv:name="commit">
      <sv:property sv:name="jcr:primaryType" sv:type="Name">
        <sv:value>mgnl:contentNode</sv:value>
      </sv:property>
      <sv:property sv:name="jcr:uuid" sv:type="String">
        <sv:value>a692c684-f070-4aef-a90b-84c8ada98468</sv:value>
      </sv:property>
      <sv:property sv:name="class" sv:type="String">
        <sv:value>info.magnolia.ui.admincentral.dialog.action.SaveDialogActionDefinition</sv:value>
      </sv:property>
      <sv:property sv:name="implementationClass" sv:type="String">
        <sv:value>info.magnolia.shop.dialog.action.ShopSaveDialogAction</sv:value>
      </sv:property>
      <sv:property sv:name="jcr:createdBy" sv:type="String">
        <sv:value>admin</sv:value>
      </sv:property>
      <sv:property sv:name="mgnl:lastModified" sv:type="Date">
        <sv:value>2013-10-20T14:11:20.251+02:00</sv:value>
      </sv:property>
      <sv:property sv:name="mgnl:lastModifiedBy" sv:type="String">
        <sv:value>superuser</sv:value>
      </sv:property>
    </sv:node>
    <sv:node sv:name="cancel">
      <sv:property sv:name="jcr:primaryType" sv:type="Name">
        <sv:value>mgnl:contentNode</sv:value>
      </sv:property>
      <sv:property sv:name="jcr:uuid" sv:type="String">
        <sv:value>47cf4a0b-f7c0-41db-8d20-e4d3301e61d5</sv:value>
      </sv:property>
      <sv:property sv:name="class" sv:type="String">
        <sv:value>info.magnolia.ui.admincentral.dialog.action.CancelDialogActionDefinition</sv:value>
      </sv:property>
      <sv:property sv:name="jcr:createdBy" sv:type="String">
        <sv:value>admin</sv:value>
      </sv:property>
      <sv:property sv:name="mgnl:lastModified" sv:type="Date">
        <sv:value>2013-10-20T09:01:08.844+02:00</sv:value>
      </sv:property>
      <sv:property sv:name="mgnl:lastModifiedBy" sv:type="String">
        <sv:value>superuser</sv:value>
      </sv:property>
    </sv:node>
  </sv:node>
  <sv:node sv:name="form">
    <sv:property sv:name="jcr:primaryType" sv:type="Name">
      <sv:value>mgnl:contentNode</sv:value>
    </sv:property>
    <sv:property sv:name="jcr:uuid" sv:type="String">
      <sv:value>5cc6f804-38c1-403d-ae78-519a5bb6d29f</sv:value>
    </sv:property>
    <sv:property sv:name="jcr:createdBy" sv:type="String">
      <sv:value>admin</sv:value>
    </sv:property>
    <sv:property sv:name="mgnl:lastModified" sv:type="Date">
      <sv:value>2013-10-20T09:01:08.844+02:00</sv:value>
    </sv:property>
    <sv:property sv:name="mgnl:lastModifiedBy" sv:type="String">
      <sv:value>superuser</sv:value>
    </sv:property>
    <sv:node sv:name="tabs">
      <sv:property sv:name="jcr:primaryType" sv:type="Name">
        <sv:value>mgnl:contentNode</sv:value>
      </sv:property>
      <sv:property sv:name="jcr:uuid" sv:type="String">
        <sv:value>4652333e-02a6-4229-b962-9d9c5256d760</sv:value>
      </sv:property>
      <sv:property sv:name="jcr:createdBy" sv:type="String">
        <sv:value>admin</sv:value>
      </sv:property>
      <sv:property sv:name="mgnl:lastModified" sv:type="Date">
        <sv:value>2013-10-25T14:06:10.202+02:00</sv:value>
      </sv:property>
      <sv:property sv:name="mgnl:lastModifiedBy" sv:type="String">
        <sv:value>superuser</sv:value>
      </sv:property>
      <sv:node sv:name="main">
        <sv:property sv:name="jcr:primaryType" sv:type="Name">
          <sv:value>mgnl:contentNode</sv:value>
        </sv:property>
        <sv:property sv:name="jcr:mixinTypes" sv:type="Name" sv:multiple="true">
          <sv:value>mix:lockable</sv:value>
        </sv:property>
        <sv:property sv:name="jcr:uuid" sv:type="String">
          <sv:value>bedd26f8-b858-4a9e-acbc-28faf8f94894</sv:value>
        </sv:property>
        <sv:property sv:name="jcr:createdBy" sv:type="String">
          <sv:value>admin</sv:value>
        </sv:property>
        <sv:property sv:name="mgnl:created" sv:type="Date">
          <sv:value>2012-05-27T21:13:38.604+02:00</sv:value>
        </sv:property>
        <sv:property sv:name="mgnl:lastModified" sv:type="Date">
          <sv:value>2013-10-20T09:03:16.459+02:00</sv:value>
        </sv:property>
        <sv:property sv:name="mgnl:lastModifiedBy" sv:type="String">
          <sv:value>superuser</sv:value>
        </sv:property>
        <sv:node sv:name="fields">
          <sv:property sv:name="jcr:primaryType" sv:type="Name">
            <sv:value>mgnl:contentNode</sv:value>
          </sv:property>
          <sv:property sv:name="jcr:uuid" sv:type="String">
            <sv:value>e6189a40-9c4d-41ee-a7a3-cd97c80caa2d</sv:value>
          </sv:property>
          <sv:property sv:name="jcr:createdBy" sv:type="String">
            <sv:value>admin</sv:value>
          </sv:property>
          <sv:property sv:name="mgnl:lastModified" sv:type="Date">
            <sv:value>2013-10-20T09:03:16.455+02:00</sv:value>
          </sv:property>
          <sv:property sv:name="mgnl:lastModifiedBy" sv:type="String">
            <sv:value>superuser</sv:value>
          </sv:property>
          <sv:node sv:name="name">
            <sv:property sv:name="jcr:primaryType" sv:type="Name">
              <sv:value>mgnl:contentNode</sv:value>
            </sv:property>
            <sv:property sv:name="jcr:mixinTypes" sv:type="Name" sv:multiple="true">
              <sv:value>mix:lockable</sv:value>
            </sv:property>
            <sv:property sv:name="jcr:uuid" sv:type="String">
              <sv:value>6883d021-2aee-4cb6-8e02-f99f8d05c8c8</sv:value>
            </sv:property>
            <sv:property sv:name="class" sv:type="String">
              <sv:value>info.magnolia.ui.form.field.definition.TextFieldDefinition</sv:value>
            </sv:property>
            <sv:property sv:name="jcr:createdBy" sv:type="String">
              <sv:value>admin</sv:value>
            </sv:property>
            <sv:property sv:name="mgnl:created" sv:type="Date">
              <sv:value>2012-05-27T21:13:38.605+02:00</sv:value>
            </sv:property>
            <sv:property sv:name="mgnl:lastModified" sv:type="Date">
              <sv:value>2013-10-20T09:03:16.455+02:00</sv:value>
            </sv:property>
            <sv:property sv:name="mgnl:lastModifiedBy" sv:type="String">
              <sv:value>superuser</sv:value>
            </sv:property>
          </sv:node>
          <sv:node sv:name="url">
            <sv:property sv:name="jcr:primaryType" sv:type="Name">
              <sv:value>mgnl:contentNode</sv:value>
            </sv:property>
            <sv:property sv:name="jcr:mixinTypes" sv:type="Name" sv:multiple="true">
              <sv:value>mix:lockable</sv:value>
            </sv:property>
            <sv:property sv:name="jcr:uuid" sv:type="String">
              <sv:value>21b10c20-076b-4463-be0a-39a56897944f</sv:value>
            </sv:property>
            <sv:property sv:name="class" sv:type="String">
              <sv:value>info.magnolia.ui.form.field.definition.TextFieldDefinition</sv:value>
            </sv:property>
            <sv:property sv:name="jcr:createdBy" sv:type="String">
              <sv:value>admin</sv:value>
            </sv:property>
            <sv:property sv:name="mgnl:activationStatus" sv:type="Boolean">
              <sv:value>false</sv:value>
            </sv:property>
            <sv:property sv:name="mgnl:created" sv:type="Date">
              <sv:value>2008-06-27T13:02:12.904+02:00</sv:value>
            </sv:property>
            <sv:property sv:name="mgnl:lastActivated" sv:type="Date">
              <sv:value>2010-03-16T15:52:38.954+01:00</sv:value>
            </sv:property>
            <sv:property sv:name="mgnl:lastActivatedBy" sv:type="String">
              <sv:value>superuser</sv:value>
            </sv:property>
            <sv:property sv:name="mgnl:lastModified" sv:type="Date">
              <sv:value>2013-10-20T09:03:16.455+02:00</sv:value>
            </sv:property>
            <sv:property sv:name="mgnl:lastModifiedBy" sv:type="String">
              <sv:value>superuser</sv:value>
            </sv:property>
          </sv:node>
          <sv:node sv:name="description">
            <sv:property sv:name="jcr:primaryType" sv:type="Name">
              <sv:value>mgnl:contentNode</sv:value>
            </sv:property>
            <sv:property sv:name="jcr:mixinTypes" sv:type="Name" sv:multiple="true">
              <sv:value>mix:lockable</sv:value>
            </sv:property>
            <sv:property sv:name="jcr:uuid" sv:type="String">
              <sv:value>568ee945-ce97-440f-a510-54b475eac75c</sv:value>
            </sv:property>
            <sv:property sv:name="class" sv:type="String">
              <sv:value>info.magnolia.ui.form.field.definition.RichTextFieldDefinition</sv:value>
            </sv:property>
            <sv:property sv:name="i18n" sv:type="Boolean">
              <sv:value>true</sv:value>
            </sv:property>
            <sv:property sv:name="jcr:createdBy" sv:type="String">
              <sv:value>admin</sv:value>
            </sv:property>
            <sv:property sv:name="mgnl:activationStatus" sv:type="Boolean">
              <sv:value>false</sv:value>
            </sv:property>
            <sv:property sv:name="mgnl:created" sv:type="Date">
              <sv:value>2012-05-27T21:13:38.605+02:00</sv:value>
            </sv:property>
            <sv:property sv:name="mgnl:lastModified" sv:type="Date">
              <sv:value>2015-07-07T14:41:58.021+02:00</sv:value>
            </sv:property>
            <sv:property sv:name="mgnl:lastModifiedBy" sv:type="String">
              <sv:value>superuser</sv:value>
            </sv:property>
          </sv:node>
        </sv:node>
      </sv:node>
      <sv:node sv:name="address">
        <sv:property sv:name="jcr:primaryType" sv:type="Name">
          <sv:value>mgnl:contentNode</sv:value>
        </sv:property>
        <sv:property sv:name="jcr:uuid" sv:type="String">
          <sv:value>9059e160-efd2-477f-bfbb-e64ccbb46bf4</sv:value>
        </sv:property>
        <sv:property sv:name="jcr:createdBy" sv:type="String">
          <sv:value>admin</sv:value>
        </sv:property>
        <sv:property sv:name="mgnl:created" sv:type="Date">
          <sv:value>2013-10-25T14:06:10.204+02:00</sv:value>
        </sv:property>
        <sv:property sv:name="mgnl:createdBy" sv:type="String">
          <sv:value>superuser</sv:value>
        </sv:property>
        <sv:property sv:name="mgnl:lastModified" sv:type="Date">
          <sv:value>2013-10-25T14:06:42.764+02:00</sv:value>
        </sv:property>
        <sv:property sv:name="mgnl:lastModifiedBy" sv:type="String">
          <sv:value>superuser</sv:value>
        </sv:property>
        <sv:node sv:name="fields">
          <sv:property sv:name="jcr:primaryType" sv:type="Name">
            <sv:value>mgnl:contentNode</sv:value>
          </sv:property>
          <sv:property sv:name="jcr:uuid" sv:type="String">
            <sv:value>86f1dfd3-cb81-47a0-a80e-1b04170b7460</sv:value>
          </sv:property>
          <sv:property sv:name="jcr:createdBy" sv:type="String">
            <sv:value>admin</sv:value>
          </sv:property>
          <sv:property sv:name="mgnl:created" sv:type="Date">
            <sv:value>2013-10-25T14:06:42.764+02:00</sv:value>
          </sv:property>
          <sv:property sv:name="mgnl:createdBy" sv:type="String">
            <sv:value>superuser</sv:value>
          </sv:property>
          <sv:property sv:name="mgnl:lastModified" sv:type="Date">
            <sv:value>2013-10-25T14:06:52.634+02:00</sv:value>
          </sv:property>
          <sv:property sv:name="mgnl:lastModifiedBy" sv:type="String">
            <sv:value>superuser</sv:value>
          </sv:property>
          <sv:node sv:name="company">
            <sv:property sv:name="jcr:primaryType" sv:type="Name">
              <sv:value>mgnl:contentNode</sv:value>
            </sv:property>
            <sv:property sv:name="jcr:mixinTypes" sv:type="Name" sv:multiple="true">
              <sv:value>mix:lockable</sv:value>
            </sv:property>
            <sv:property sv:name="jcr:uuid" sv:type="String">
              <sv:value>8092434f-b879-4d0b-a979-aecaf82afa4d</sv:value>
            </sv:property>
            <sv:property sv:name="class" sv:type="String">
              <sv:value>info.magnolia.ui.form.field.definition.TextFieldDefinition</sv:value>
            </sv:property>
            <sv:property sv:name="i18n" sv:type="Boolean">
              <sv:value>true</sv:value>
            </sv:property>
            <sv:property sv:name="jcr:createdBy" sv:type="String">
              <sv:value>admin</sv:value>
            </sv:property>
            <sv:property sv:name="mgnl:activationStatus" sv:type="Boolean">
              <sv:value>false</sv:value>
            </sv:property>
            <sv:property sv:name="mgnl:created" sv:type="Date">
              <sv:value>2008-06-27T13:02:12.904+02:00</sv:value>
            </sv:property>
            <sv:property sv:name="mgnl:lastActivated" sv:type="Date">
              <sv:value>2010-03-16T15:52:38.954+01:00</sv:value>
            </sv:property>
            <sv:property sv:name="mgnl:lastActivatedBy" sv:type="String">
              <sv:value>superuser</sv:value>
            </sv:property>
            <sv:property sv:name="mgnl:lastModified" sv:type="Date">
              <sv:value>2015-07-07T14:42:34.150+02:00</sv:value>
            </sv:property>
            <sv:property sv:name="mgnl:lastModifiedBy" sv:type="String">
              <sv:value>superuser</sv:value>
            </sv:property>
            <sv:property sv:name="required" sv:type="String">
              <sv:value>true</sv:value>
            </sv:property>
          </sv:node>
          <sv:node sv:name="company2">
            <sv:property sv:name="jcr:primaryType" sv:type="Name">
              <sv:value>mgnl:contentNode</sv:value>
            </sv:property>
            <sv:property sv:name="jcr:mixinTypes" sv:type="Name" sv:multiple="true">
              <sv:value>mix:lockable</sv:value>
            </sv:property>
            <sv:property sv:name="jcr:uuid" sv:type="String">
              <sv:value>0653f016-2e24-44a4-ac6b-3d56dc2c4b47</sv:value>
            </sv:property>
            <sv:property sv:name="class" sv:type="String">
              <sv:value>info.magnolia.ui.form.field.definition.TextFieldDefinition</sv:value>
            </sv:property>
            <sv:property sv:name="i18n" sv:type="Boolean">
              <sv:value>true</sv:value>
            </sv:property>
            <sv:property sv:name="jcr:createdBy" sv:type="String">
              <sv:value>admin</sv:value>
            </sv:property>
            <sv:property sv:name="mgnl:activationStatus" sv:type="Boolean">
              <sv:value>false</sv:value>
            </sv:property>
            <sv:property sv:name="mgnl:created" sv:type="Date">
              <sv:value>2008-06-27T13:02:12.904+02:00</sv:value>
            </sv:property>
            <sv:property sv:name="mgnl:lastActivated" sv:type="Date">
              <sv:value>2010-03-16T15:52:38.954+01:00</sv:value>
            </sv:property>
            <sv:property sv:name="mgnl:lastActivatedBy" sv:type="String">
              <sv:value>superuser</sv:value>
            </sv:property>
            <sv:property sv:name="mgnl:lastModified" sv:type="Date">
              <sv:value>2015-07-07T14:42:52.971+02:00</sv:value>
            </sv:property>
            <sv:property sv:name="mgnl:lastModifiedBy" sv:type="String">
              <sv:value>superuser</sv:value>
            </sv:property>
          </sv:node>
          <sv:node sv:name="address">
            <sv:property sv:name="jcr:primaryType" sv:type="Name">
              <sv:value>mgnl:contentNode</sv:value>
            </sv:property>
            <sv:property sv:name="jcr:mixinTypes" sv:type="Name" sv:multiple="true">
              <sv:value>mix:lockable</sv:value>
            </sv:property>
            <sv:property sv:name="jcr:uuid" sv:type="String">
              <sv:value>588c5043-14da-4cc8-896a-8d9c1fbb3191</sv:value>
            </sv:property>
            <sv:property sv:name="class" sv:type="String">
              <sv:value>info.magnolia.ui.form.field.definition.TextFieldDefinition</sv:value>
            </sv:property>
            <sv:property sv:name="jcr:createdBy" sv:type="String">
              <sv:value>admin</sv:value>
            </sv:property>
            <sv:property sv:name="mgnl:activationStatus" sv:type="Boolean">
              <sv:value>false</sv:value>
            </sv:property>
            <sv:property sv:name="mgnl:created" sv:type="Date">
              <sv:value>2008-06-27T13:02:12.904+02:00</sv:value>
            </sv:property>
            <sv:property sv:name="mgnl:lastActivated" sv:type="Date">
              <sv:value>2010-03-16T15:52:38.954+01:00</sv:value>
            </sv:property>
            <sv:property sv:name="mgnl:lastActivatedBy" sv:type="String">
              <sv:value>superuser</sv:value>
            </sv:property>
            <sv:property sv:name="mgnl:lastModified" sv:type="Date">
              <sv:value>2013-10-25T14:07:27.540+02:00</sv:value>
            </sv:property>
            <sv:property sv:name="mgnl:lastModifiedBy" sv:type="String">
              <sv:value>superuser</sv:value>
            </sv:property>
          </sv:node>
          <sv:node sv:name="address2">
            <sv:property sv:name="jcr:primaryType" sv:type="Name">
              <sv:value>mgnl:contentNode</sv:value>
            </sv:property>
            <sv:property sv:name="jcr:mixinTypes" sv:type="Name" sv:multiple="true">
              <sv:value>mix:lockable</sv:value>
            </sv:property>
            <sv:property sv:name="jcr:uuid" sv:type="String">
              <sv:value>587c7955-5767-46b5-905f-4aa2aa92f5d9</sv:value>
            </sv:property>
            <sv:property sv:name="class" sv:type="String">
              <sv:value>info.magnolia.ui.form.field.definition.TextFieldDefinition</sv:value>
            </sv:property>
            <sv:property sv:name="jcr:createdBy" sv:type="String">
              <sv:value>admin</sv:value>
            </sv:property>
            <sv:property sv:name="mgnl:activationStatus" sv:type="Boolean">
              <sv:value>false</sv:value>
            </sv:property>
            <sv:property sv:name="mgnl:created" sv:type="Date">
              <sv:value>2008-06-27T13:02:12.904+02:00</sv:value>
            </sv:property>
            <sv:property sv:name="mgnl:lastActivated" sv:type="Date">
              <sv:value>2010-03-16T15:52:38.954+01:00</sv:value>
            </sv:property>
            <sv:property sv:name="mgnl:lastActivatedBy" sv:type="String">
              <sv:value>superuser</sv:value>
            </sv:property>
            <sv:property sv:name="mgnl:lastModified" sv:type="Date">
              <sv:value>2013-10-25T14:07:29.842+02:00</sv:value>
            </sv:property>
            <sv:property sv:name="mgnl:lastModifiedBy" sv:type="String">
              <sv:value>superuser</sv:value>
            </sv:property>
          </sv:node>
          <sv:node sv:name="city">
            <sv:property sv:name="jcr:primaryType" sv:type="Name">
              <sv:value>mgnl:contentNode</sv:value>
            </sv:property>
            <sv:property sv:name="jcr:mixinTypes" sv:type="Name" sv:multiple="true">
              <sv:value>mix:lockable</sv:value>
            </sv:property>
            <sv:property sv:name="jcr:uuid" sv:type="String">
              <sv:value>b0414bf2-dd4d-4ef1-8211-92ae92abd45d</sv:value>
            </sv:property>
            <sv:property sv:name="class" sv:type="String">
              <sv:value>info.magnolia.ui.form.field.definition.TextFieldDefinition</sv:value>
            </sv:property>
            <sv:property sv:name="jcr:createdBy" sv:type="String">
              <sv:value>admin</sv:value>
            </sv:property>
            <sv:property sv:name="mgnl:activationStatus" sv:type="Boolean">
              <sv:value>false</sv:value>
            </sv:property>
            <sv:property sv:name="mgnl:created" sv:type="Date">
              <sv:value>2008-06-27T13:02:12.904+02:00</sv:value>
            </sv:property>
            <sv:property sv:name="mgnl:lastActivated" sv:type="Date">
              <sv:value>2010-03-16T15:52:38.954+01:00</sv:value>
            </sv:property>
            <sv:property sv:name="mgnl:lastActivatedBy" sv:type="String">
              <sv:value>superuser</sv:value>
            </sv:property>
            <sv:property sv:name="mgnl:lastModified" sv:type="Date">
              <sv:value>2013-10-25T14:07:32.207+02:00</sv:value>
            </sv:property>
            <sv:property sv:name="mgnl:lastModifiedBy" sv:type="String">
              <sv:value>superuser</sv:value>
            </sv:property>
          </sv:node>
          <sv:node sv:name="zip">
            <sv:property sv:name="jcr:primaryType" sv:type="Name">
              <sv:value>mgnl:contentNode</sv:value>
            </sv:property>
            <sv:property sv:name="jcr:mixinTypes" sv:type="Name" sv:multiple="true">
              <sv:value>mix:lockable</sv:value>
            </sv:property>
            <sv:property sv:name="jcr:uuid" sv:type="String">
              <sv:value>5cce6fa4-0cca-4eec-b808-87a481ab8303</sv:value>
            </sv:property>
            <sv:property sv:name="class" sv:type="String">
              <sv:value>info.magnolia.ui.form.field.definition.TextFieldDefinition</sv:value>
            </sv:property>
            <sv:property sv:name="jcr:createdBy" sv:type="String">
              <sv:value>admin</sv:value>
            </sv:property>
            <sv:property sv:name="mgnl:activationStatus" sv:type="Boolean">
              <sv:value>false</sv:value>
            </sv:property>
            <sv:property sv:name="mgnl:created" sv:type="Date">
              <sv:value>2008-06-27T13:02:12.904+02:00</sv:value>
            </sv:property>
            <sv:property sv:name="mgnl:lastActivated" sv:type="Date">
              <sv:value>2010-03-16T15:52:38.954+01:00</sv:value>
            </sv:property>
            <sv:property sv:name="mgnl:lastActivatedBy" sv:type="String">
              <sv:value>superuser</sv:value>
            </sv:property>
            <sv:property sv:name="mgnl:lastModified" sv:type="Date">
              <sv:value>2013-10-25T14:07:58.272+02:00</sv:value>
            </sv:property>
            <sv:property sv:name="mgnl:lastModifiedBy" sv:type="String">
              <sv:value>superuser</sv:value>
            </sv:property>
          </sv:node>
          <sv:node sv:name="state">
            <sv:property sv:name="jcr:primaryType" sv:type="Name">
              <sv:value>mgnl:contentNode</sv:value>
            </sv:property>
            <sv:property sv:name="jcr:mixinTypes" sv:type="Name" sv:multiple="true">
              <sv:value>mix:lockable</sv:value>
            </sv:property>
            <sv:property sv:name="jcr:uuid" sv:type="String">
              <sv:value>a24202bb-59e1-494b-8979-4caf918d7987</sv:value>
            </sv:property>
            <sv:property sv:name="class" sv:type="String">
              <sv:value>info.magnolia.ui.form.field.definition.TextFieldDefinition</sv:value>
            </sv:property>
            <sv:property sv:name="jcr:createdBy" sv:type="String">
              <sv:value>admin</sv:value>
            </sv:property>
            <sv:property sv:name="mgnl:activationStatus" sv:type="Boolean">
              <sv:value>false</sv:value>
            </sv:property>
            <sv:property sv:name="mgnl:created" sv:type="Date">
              <sv:value>2008-06-27T13:02:12.904+02:00</sv:value>
            </sv:property>
            <sv:property sv:name="mgnl:lastActivated" sv:type="Date">
              <sv:value>2010-03-16T15:52:38.954+01:00</sv:value>
            </sv:property>
            <sv:property sv:name="mgnl:lastActivatedBy" sv:type="String">
              <sv:value>superuser</sv:value>
            </sv:property>
            <sv:property sv:name="mgnl:lastModified" sv:type="Date">
              <sv:value>2013-10-25T14:07:36.681+02:00</sv:value>
            </sv:property>
            <sv:property sv:name="mgnl:lastModifiedBy" sv:type="String">
              <sv:value>superuser</sv:value>
            </sv:property>
          </sv:node>
          <sv:node sv:name="country">
            <sv:property sv:name="jcr:primaryType" sv:type="Name">
              <sv:value>mgnl:contentNode</sv:value>
            </sv:property>
            <sv:property sv:name="jcr:mixinTypes" sv:type="Name" sv:multiple="true">
              <sv:value>mix:lockable</sv:value>
            </sv:property>
            <sv:property sv:name="jcr:uuid" sv:type="String">
              <sv:value>d2416a69-7eb7-493b-80ea-841b69a5095c</sv:value>
            </sv:property>
            <sv:property sv:name="class" sv:type="String">
              <sv:value>info.magnolia.ui.form.field.definition.TextFieldDefinition</sv:value>
            </sv:property>
            <sv:property sv:name="i18n" sv:type="Boolean">
              <sv:value>true</sv:value>
            </sv:property>
            <sv:property sv:name="jcr:createdBy" sv:type="String">
              <sv:value>admin</sv:value>
            </sv:property>
            <sv:property sv:name="mgnl:activationStatus" sv:type="Boolean">
              <sv:value>false</sv:value>
            </sv:property>
            <sv:property sv:name="mgnl:created" sv:type="Date">
              <sv:value>2008-06-27T13:02:12.904+02:00</sv:value>
            </sv:property>
            <sv:property sv:name="mgnl:lastActivated" sv:type="Date">
              <sv:value>2010-03-16T15:52:38.954+01:00</sv:value>
            </sv:property>
            <sv:property sv:name="mgnl:lastActivatedBy" sv:type="String">
              <sv:value>superuser</sv:value>
            </sv:property>
            <sv:property sv:name="mgnl:lastModified" sv:type="Date">
              <sv:value>2015-07-07T14:43:35.839+02:00</sv:value>
            </sv:property>
            <sv:property sv:name="mgnl:lastModifiedBy" sv:type="String">
              <sv:value>superuser</sv:value>
            </sv:property>
          </sv:node>
          <sv:node sv:name="phone">
            <sv:property sv:name="jcr:primaryType" sv:type="Name">
              <sv:value>mgnl:contentNode</sv:value>
            </sv:property>
            <sv:property sv:name="jcr:mixinTypes" sv:type="Name" sv:multiple="true">
              <sv:value>mix:lockable</sv:value>
            </sv:property>
            <sv:property sv:name="jcr:uuid" sv:type="String">
              <sv:value>8fb847b4-bb48-4261-a1d2-ac2f7d38cef6</sv:value>
            </sv:property>
            <sv:property sv:name="class" sv:type="String">
              <sv:value>info.magnolia.ui.form.field.definition.TextFieldDefinition</sv:value>
            </sv:property>
            <sv:property sv:name="jcr:createdBy" sv:type="String">
              <sv:value>admin</sv:value>
            </sv:property>
            <sv:property sv:name="mgnl:activationStatus" sv:type="Boolean">
              <sv:value>false</sv:value>
            </sv:property>
            <sv:property sv:name="mgnl:created" sv:type="Date">
              <sv:value>2008-06-27T13:02:12.904+02:00</sv:value>
            </sv:property>
            <sv:property sv:name="mgnl:lastActivated" sv:type="Date">
              <sv:value>2010-03-16T15:52:38.954+01:00</sv:value>
            </sv:property>
            <sv:property sv:name="mgnl:lastActivatedBy" sv:type="String">
              <sv:value>superuser</sv:value>
            </sv:property>
            <sv:property sv:name="mgnl:lastModified" sv:type="Date">
              <sv:value>2013-10-25T14:07:41.045+02:00</sv:value>
            </sv:property>
            <sv:property sv:name="mgnl:lastModifiedBy" sv:type="String">
              <sv:value>superuser</sv:value>
            </sv:property>
          </sv:node>
          <sv:node sv:name="email">
            <sv:property sv:name="jcr:primaryType" sv:type="Name">
              <sv:value>mgnl:contentNode</sv:value>
            </sv:property>
            <sv:property sv:name="jcr:mixinTypes" sv:type="Name" sv:multiple="true">
              <sv:value>mix:lockable</sv:value>
            </sv:property>
            <sv:property sv:name="jcr:uuid" sv:type="String">
              <sv:value>7381fd8a-2521-4e87-8421-00a98f564270</sv:value>
            </sv:property>
            <sv:property sv:name="class" sv:type="String">
              <sv:value>info.magnolia.ui.form.field.definition.TextFieldDefinition</sv:value>
            </sv:property>
            <sv:property sv:name="jcr:createdBy" sv:type="String">
              <sv:value>admin</sv:value>
            </sv:property>
            <sv:property sv:name="mgnl:activationStatus" sv:type="Boolean">
              <sv:value>false</sv:value>
            </sv:property>
            <sv:property sv:name="mgnl:created" sv:type="Date">
              <sv:value>2008-06-27T13:02:12.904+02:00</sv:value>
            </sv:property>
            <sv:property sv:name="mgnl:lastActivated" sv:type="Date">
              <sv:value>2010-03-16T15:52:38.954+01:00</sv:value>
            </sv:property>
            <sv:property sv:name="mgnl:lastActivatedBy" sv:type="String">
              <sv:value>superuser</sv:value>
            </sv:property>
            <sv:property sv:name="mgnl:lastModified" sv:type="Date">
              <sv:value>2013-10-25T14:07:43.608+02:00</sv:value>
            </sv:property>
            <sv:property sv:name="mgnl:lastModifiedBy" sv:type="String">
              <sv:value>superuser</sv:value>
            </sv:property>
          </sv:node>
        </sv:node>
      </sv:node>
      <sv:node sv:name="logo">
        <sv:property sv:name="jcr:primaryType" sv:type="Name">
          <sv:value>mgnl:contentNode</sv:value>
        </sv:property>
        <sv:property sv:name="jcr:mixinTypes" sv:type="Name" sv:multiple="true">
          <sv:value>mix:lockable</sv:value>
        </sv:property>
        <sv:property sv:name="jcr:uuid" sv:type="String">
          <sv:value>0d3d5709-cb0b-46a4-a7a4-d65fe3980f1f</sv:value>
        </sv:property>
        <sv:property sv:name="jcr:createdBy" sv:type="String">
          <sv:value>admin</sv:value>
        </sv:property>
        <sv:property sv:name="mgnl:created" sv:type="Date">
          <sv:value>2012-05-27T21:21:08.619+02:00</sv:value>
        </sv:property>
        <sv:property sv:name="mgnl:lastModified" sv:type="Date">
          <sv:value>2013-10-20T09:03:22.289+02:00</sv:value>
        </sv:property>
        <sv:property sv:name="mgnl:lastModifiedBy" sv:type="String">
          <sv:value>superuser</sv:value>
        </sv:property>
        <sv:node sv:name="fields">
          <sv:property sv:name="jcr:primaryType" sv:type="Name">
            <sv:value>mgnl:contentNode</sv:value>
          </sv:property>
          <sv:property sv:name="jcr:uuid" sv:type="String">
            <sv:value>1500dd90-f910-4936-962f-87bdcbb3b0ec</sv:value>
          </sv:property>
          <sv:property sv:name="jcr:createdBy" sv:type="String">
            <sv:value>admin</sv:value>
          </sv:property>
          <sv:property sv:name="mgnl:lastModified" sv:type="Date">
            <sv:value>2013-10-20T09:03:22.282+02:00</sv:value>
          </sv:property>
          <sv:property sv:name="mgnl:lastModifiedBy" sv:type="String">
            <sv:value>superuser</sv:value>
          </sv:property>
          <sv:node sv:name="logoUUID_bak">
            <sv:property sv:name="jcr:primaryType" sv:type="Name">
              <sv:value>mgnl:contentNode</sv:value>
            </sv:property>
            <sv:property sv:name="jcr:mixinTypes" sv:type="Name" sv:multiple="true">
              <sv:value>mix:lockable</sv:value>
            </sv:property>
            <sv:property sv:name="jcr:uuid" sv:type="String">
              <sv:value>ded3daf3-eb7f-4a66-8189-08dfa85443b1</sv:value>
            </sv:property>
            <sv:property sv:name="appName" sv:type="String">
              <sv:value>assets</sv:value>
            </sv:property>
            <sv:property sv:name="class" sv:type="String">
              <sv:value>info.magnolia.ui.form.field.definition.LinkFieldDefinition</sv:value>
            </sv:property>
            <sv:property sv:name="jcr:createdBy" sv:type="String">
              <sv:value>admin</sv:value>
            </sv:property>
            <sv:property sv:name="mgnl:activationStatus" sv:type="Boolean">
              <sv:value>false</sv:value>
            </sv:property>
            <sv:property sv:name="mgnl:created" sv:type="Date">
              <sv:value>2012-05-27T21:13:38.605+02:00</sv:value>
            </sv:property>
            <sv:property sv:name="mgnl:lastModified" sv:type="Date">
              <sv:value>2013-10-20T09:03:22.282+02:00</sv:value>
            </sv:property>
            <sv:property sv:name="mgnl:lastModifiedBy" sv:type="String">
              <sv:value>superuser</sv:value>
            </sv:property>
            <sv:property sv:name="targetWorkspace" sv:type="String">
              <sv:value>dam</sv:value>
            </sv:property>
            <sv:node sv:name="identifierToPathConverter">
              <sv:property sv:name="jcr:primaryType" sv:type="Name">
                <sv:value>mgnl:contentNode</sv:value>
              </sv:property>
              <sv:property sv:name="jcr:uuid" sv:type="String">
                <sv:value>3528171b-4db9-4d0f-a150-fc3c25879d14</sv:value>
              </sv:property>
              <sv:property sv:name="class" sv:type="String">
                <sv:value>info.magnolia.dam.app.assets.field.translator.AssetCompositeIdKeyTranslator</sv:value>
              </sv:property>
              <sv:property sv:name="jcr:createdBy" sv:type="String">
                <sv:value>admin</sv:value>
              </sv:property>
              <sv:property sv:name="mgnl:lastModified" sv:type="Date">
                <sv:value>2013-10-20T09:03:22.282+02:00</sv:value>
              </sv:property>
              <sv:property sv:name="mgnl:lastModifiedBy" sv:type="String">
                <sv:value>superuser</sv:value>
              </sv:property>
            </sv:node>
            <sv:node sv:name="contentPreviewDefinition">
              <sv:property sv:name="jcr:primaryType" sv:type="Name">
                <sv:value>mgnl:contentNode</sv:value>
              </sv:property>
              <sv:property sv:name="jcr:uuid" sv:type="String">
                <sv:value>27dc24ae-bea0-47ab-b9b5-b788d0c22b75</sv:value>
              </sv:property>
              <sv:property sv:name="contentPreviewClass" sv:type="String">
                <sv:value>info.magnolia.dam.app.ui.field.DamFilePreviewComponent</sv:value>
              </sv:property>
              <sv:property sv:name="jcr:createdBy" sv:type="String">
                <sv:value>admin</sv:value>
              </sv:property>
              <sv:property sv:name="mgnl:lastModified" sv:type="Date">
                <sv:value>2013-10-20T09:03:22.282+02:00</sv:value>
              </sv:property>
              <sv:property sv:name="mgnl:lastModifiedBy" sv:type="String">
                <sv:value>superuser</sv:value>
              </sv:property>
            </sv:node>
          </sv:node>
          <sv:node sv:name="logoUUID">
            <sv:property sv:name="jcr:primaryType" sv:type="Name">
              <sv:value>mgnl:contentNode</sv:value>
            </sv:property>
            <sv:property sv:name="jcr:uuid" sv:type="String">
              <sv:value>aa21d3d5-12e0-47df-ae80-f21edbbf75b5</sv:value>
            </sv:property>
            <sv:property sv:name="class" sv:type="String">
              <sv:value>info.magnolia.ui.form.field.definition.StaticFieldDefinition</sv:value>
            </sv:property>
            <sv:property sv:name="controlType" sv:type="String">
              <sv:value>shopDam</sv:value>
            </sv:property>
            <sv:property sv:name="jcr:createdBy" sv:type="String">
              <sv:value>admin</sv:value>
            </sv:property>
            <sv:property sv:name="mgnl:activationStatus" sv:type="Boolean">
              <sv:value>false</sv:value>
            </sv:property>
            <sv:property sv:name="mgnl:created" sv:type="String">
              <sv:value>2004-11-03T08:48:09.632+01:00</sv:value>
            </sv:property>
            <sv:property sv:name="mgnl:lastActivated" sv:type="Date">
              <sv:value>2006-05-01T21:47:58.230+02:00</sv:value>
            </sv:property>
            <sv:property sv:name="mgnl:lastActivatedBy" sv:type="String">
              <sv:value>superuser</sv:value>
            </sv:property>
            <sv:property sv:name="mgnl:lastModified" sv:type="Date">
              <sv:value>2013-10-20T09:03:22.282+02:00</sv:value>
            </sv:property>
            <sv:property sv:name="mgnl:lastModifiedBy" sv:type="String">
              <sv:value>superuser</sv:value>
            </sv:property>
            <sv:property sv:name="value" sv:type="String">
              <sv:value>Field not yet supported</sv:value>
            </sv:property>
          </sv:node>
          <sv:node sv:name="terms">
            <sv:property sv:name="jcr:primaryType" sv:type="Name">
              <sv:value>mgnl:contentNode</sv:value>
            </sv:property>
            <sv:property sv:name="jcr:uuid" sv:type="String">
              <sv:value>32ff6717-d8dc-4649-a073-b9da3cfedd9f</sv:value>
            </sv:property>
            <sv:property sv:name="class" sv:type="String">
              <sv:value>info.magnolia.ui.form.field.definition.StaticFieldDefinition</sv:value>
            </sv:property>
            <sv:property sv:name="controlType" sv:type="String">
              <sv:value>shopDam</sv:value>
            </sv:property>
            <sv:property sv:name="jcr:createdBy" sv:type="String">
              <sv:value>admin</sv:value>
            </sv:property>
            <sv:property sv:name="mgnl:activationStatus" sv:type="Boolean">
              <sv:value>false</sv:value>
            </sv:property>
            <sv:property sv:name="mgnl:created" sv:type="String">
              <sv:value>2004-11-03T08:48:09.632+01:00</sv:value>
            </sv:property>
            <sv:property sv:name="mgnl:lastActivated" sv:type="Date">
              <sv:value>2006-05-01T21:47:58.230+02:00</sv:value>
            </sv:property>
            <sv:property sv:name="mgnl:lastActivatedBy" sv:type="String">
              <sv:value>superuser</sv:value>
            </sv:property>
            <sv:property sv:name="mgnl:lastModified" sv:type="Date">
              <sv:value>2013-10-20T09:03:22.282+02:00</sv:value>
            </sv:property>
            <sv:property sv:name="mgnl:lastModifiedBy" sv:type="String">
              <sv:value>superuser</sv:value>
            </sv:property>
            <sv:property sv:name="value" sv:type="String">
              <sv:value>Field not yet supported</sv:value>
            </sv:property>
          </sv:node>
        </sv:node>
      </sv:node>
    </sv:node>
  </sv:node>
</sv:node>
